{"timeAliveStart":1410620110556,"emoteSet":"","filterLinks":false,"filterOffensive":true,"maxViewers":0,"filterSymbolsPercent":50,"filterCaps":false,"cooldown":5,"streamCount":0,"subsRegsMinusLinks":false,"logChat":false,"staticChannel":false,"subscriberAlert":false,"urbanEnabled":true,"filterCapsPercent":50,"topic":"","repeatedCommands":[],"extraLifeID":0,"steamID":"76561198077560571","timeoutDuration":600,"filterCapsMinCapitals":6,"enableThrow":true,"scheduledCommands":[],"signKicks":false,"updateDelay":120,"owners":[],"filterCapsMinCharacters":0,"streamAlive":false,"filterEmotesMax":4,"filterEmotesSingle":false,"filterSymbols":false,"filterColors":false,"commands":[{"count":3,"restriction":1,"value":"( ͡° ͜ʖ ͡°)","key":"lenny"},{"count":11,"restriction":1,"value":"(_GAME_)","key":"g"},{"count":8,"restriction":1,"value":"8","key":"deathcount"},{"count":4,"restriction":1,"value":"JJ, giggle for us dammit.","key":"giggle"},{"count":4,"restriction":1,"value":"ヽ( ･∀･)ﾉ┌┛(_PARAMETER_)","key":"kick"},{"count":2,"restriction":1,"value":"You can blame it all on (_PARAMETER_)~","key":"coebotcomeback"},{"count":3,"restriction":1,"value":"(╯°□°）╯彡┴─┴","key":"tableflip"},{"count":5,"restriction":1,"value":"(╬〇д〇)凸","key":"sassy"},{"count":9,"restriction":1,"value":"JJ is a French Canadian from Quebec. Kappa","key":"aboutjj"},{"count":9,"restriction":1,"value":"I am totally a French Canadian from Quebec.","key":"jj"},{"count":25,"restriction":1,"value":"(_VIEWERS_)","key":"v"},{"count":3,"restriction":1,"value":"Bootiful.","key":"julie"},{"count":11,"restriction":1,"value":"( ・_・)ノ (_PARAMETER_)","key":"slap"},{"count":6,"restriction":1,"value":"Why you heff to be mad? It's only (_PARAMETER_).","key":"mad"},{"count":2,"restriction":1,"value":"(　-_･) ︻デ═一 (_PARAMETER_)","key":"shoot"},{"count":10,"restriction":1,"value":"\"Couldn't find any results, sorry.\"","key":"heavie"},{"count":14,"restriction":1,"value":"( ◉◞౪◟◉) My ass cheeks are clenched. My body is reggie.","key":"hype"},{"count":6,"restriction":1,"value":"\"Another word for spaz; dingus.\" Kappa","key":"mega"},{"count":3,"restriction":1,"value":"Praise (_PARAMETER_)! （☝ ՞ਊ ՞）☝","key":"praise"},{"count":8,"restriction":1,"value":"(╯°□°）╯彡 shade","key":"shade"},{"count":23,"restriction":1,"value":"(ノ^∇^) Welcome to follow!","key":"welcome"},{"count":13,"restriction":1,"value":"Dew it for the vine. ( ･ิω･ิ)","key":"palpatine"},{"count":5,"restriction":1,"value":"Pick a fucking card already.","key":"cah"}],"autoReplies":[{"response":"Sssshhhh, JJ doesn't know how to use Coebot.","trigger":"\\Qsshhh\\E"},{"response":"Bye! Thanks for stahping by.","trigger":"\\Qbye\\E"},{"response":"Calm your tits, the stream will come back soon. Probably.","trigger":"\\Qpicnic\\E"},{"response":"You're welcome.","trigger":"\\Qthanks coebot\\E"},{"response":"ರ_ರ jfc, grow up guys","trigger":"\\Qhard\\E"},{"response":"(；¬д¬)","trigger":"\\Qugh\\E"},{"response":"Hiya! Welcome to the stream.","trigger":"\\Qhi\\E"},{"response":"Heyo! Welcome to the stream.","trigger":"\\Qhey\\E"},{"response":"http:\/\/i.imgur.com\/gT908E7.jpg","trigger":".*\\Qdickbutt\\E.*"},{"response":"In the butt. Kappa","trigger":".*\\Qwhat what\\E.*"},{"response":"\"Jia is just cumming constantly. Every time he sighs in frustration, after living in a dorm with guys for a year... I know that sound.\"","trigger":".*\\Qsigh\\E.*"},{"response":"( \u2022_\u2022) ( \u2022_\u2022)>⌐■-■ (⌐■_■)","trigger":"\\Qdeal with it\\E"},{"response":"I love you too, random citizen. (◡\u203F◡✿)","trigger":"\\Qi love you coebot\\E"},{"response":"凸ಠ益ಠ)凸","trigger":".*\\Qfuck you\\E.*"},{"response":"MMMMMbreh","trigger":"\\Qgg\\E"}],"gamerTag":"","useTopic":true,"mode":2,"subscriberRegulars":false,"announceJoinParts":false,"offensiveWords":["cheavie"],"runningMaxViewers":0,"sincePunish":1406778042285,"commandPrefix":"+","subMessage":"(_1_) has subscribed!","maxViewersStream":0,"wpTimer":false,"useFilters":false,"topicTime":0,"commercialLength":30,"raidWhitelist":[],"clickToTweetFormat":"Checkout (_CHANNEL_URL_) playing (_GAME_) on @TwitchTV","regulars":["hiragirin"],"maxviewerDate":"","enableWarnings":true,"punishCount":7,"permittedDomains":[],"moderators":[],"filterEmotes":false,"filterMe":false,"filterMaxLength":500,"filterSymbolsMin":5,"lastfm":"","quotes":["\"How can he be a walker if he's sitting?\"","\"Welcome to follow.\"","\"Ohana means family, and family means nobody gets left behind.\"","Jia is just cumming constantly. Every time he sighs in frustration, after living in a dorm with guys for a year... I know that sound."],"sinceWp":1405650510011,"ignoredUsers":[],"wpCount":0,"bullet":"coeBot","banPhraseSeverity":99}